Workbook

Sheet Análisis de precios
A4: CLIENTE: | B4: POLIUREA CONCEPCION
A5: OBRA:
A6: FECHA:
A7: CONTACTO:
A8: ANÁLISIS DE PRECIOS
A10: RUBRO | B10: ÍTEM | C10: DENOMINACIÓN | D10: UNIDAD | E10: CANTIDAD | G10: PRECIO UNITARIO | H10: PRECIO PARCIAL | I10: PRECIO RUBRO | K10: % ITEM | L10: % RUBRO | N10: Cantidad parcial | O10: Precio unitario | P10: Precio parcial
B11: 1 | C11: APLICACIÓN DE DESMOPOL + SELLADO | D11: M2 | E11: 170 | G11: =SUM(G12:G19) -> 43971.834 | H11: =+E11*G11 -> 7475211.8 | Q11: CANT PERSONAS | R11: DIAS TOTALES | S11: DIAS DE OBRA
A12: MO | C12: Oficial | D12: hs | E12: =16/E11 -> 0.094117647 | F12: 8234.07 | G12: =+E12*F12 -> 774.97129 | N12: =E12*$E$11 -> 16 | O12: =+F12 -> 8234.07 | P12: =N12*O12 -> 131745.12 | Q12: 2 | R12: =+N12/8 -> 2 | S12: =+R12/Q12 -> 1
A13: MO | C13: Ayudante | D13: hs | E13: =16/E11 -> 0.094117647 | F13: 6358.07 | G13: =+E13*F13 -> 598.40659 | N13: =E13*$E$11 -> 16 | O13: =+F13 -> 6358.07 | P13: =N13*O13 -> 101729.12 | Q13: 2 | R13: =+N13/8 -> 2 | S13: =+R13/Q13 -> 1
A14: MAT | C14: bersell | D14: kg | E14: =20/E11 -> 0.11764706 | F14: 9500 | G14: =+E14*F14 -> 1117.6471 | N14: =E14*$E$11 -> 20 | O14: =+F14 -> 9500 | P14: =N14*O14 -> 190000
A15: MAT | C15: Pincel | D15: U | E15: =3/E11 -> 0.017647059 | F15: 2100 | G15: =+E15*F15 -> 37.058824 | N15: =E15*$E$11 -> 3 | O15: =+F15 -> 2100 | P15: =N15*O15 -> 6300
A16: MAT | C16: Rodillo | D16: U | E16: =3/E11 -> 0.017647059 | F16: 6600 | G16: =+E16*F16 -> 116.47059 | N16: =E16*$E$11 -> 3 | O16: =+F16 -> 6600 | P16: =N16*O16 -> 19800
A17: MAT | C17: Primer pu 1000 | D17: lts | E17: 0.3 | F17: =12.57*1520 -> 19106.4 | G17: =+E17*F17 -> 5731.92 | N17: =E17*$E$11 -> 51 | O17: =+F17 -> 19106.4 | P17: =N17*O17 -> 974426.4
A18: MAT | C18: Poliurea en caliente | D18: kg | E18: 1.5 | F18: =13*1520 -> 19760 | G18: =+E18*F18 -> 29640 | N18: =E18*$E$11 -> 255 | O18: =+F18 -> 19760 | P18: =N18*O18 -> 5038800
A19: MAT | C19: Alifatico | D19: lts | E19: 0.3 | F19: =13.06*1520 -> 19851.2 | G19: =+E19*F19 -> 5955.36 | N19: =E19*$E$11 -> 51 | O19: =+F19 -> 19851.2 | P19: =N19*O19 -> 1012411.2
B20: 2 | C20: APLICACIÓN DE DESMOPOL + ARENA | D20: M2 | E20: 150 | G20: =SUM(G21:G28) -> 0 | H20: =+E20*G20 -> 0 | Q20: CANT PERSONAS | R20: DIAS TOTALES | S20: DIAS DE OBRA
A21: MO | C21: Oficial | D21: hs | E21: =0/E20 -> 0 | F21: 8160.48 | G21: =+E21*F21 -> 0 | N21: =E21*$E$20 -> 0 | O21: =+F21 -> 8160.48 | P21: =N21*O21 -> 0 | Q21: 2 | R21: =+N21/8 -> 0 | S21: =+R21/Q21 -> 0
A22: MO | C22: Ayudante | D22: hs | E22: =0/E20 -> 0 | F22: 6358.07 | G22: =+E22*F22 -> 0 | N22: =E22*$E$20 -> 0 | O22: =+F22 -> 6358.07 | P22: =N22*O22 -> 0 | Q22: 2 | R22: =+N22/8 -> 0 | S22: =+R22/Q22 -> 0
A23: MAT | C23: bersell | D23: kg | E23: =0/E20 -> 0 | F23: 9500 | G23: =+E23*F23 -> 0 | N23: =E23*$E$20 -> 0 | O23: =+F23 -> 9500 | P23: =N23*O23 -> 0
A24: MAT | C24: Pincel | D24: U | E24: =0/E20 -> 0 | F24: 2200 | G24: =+E24*F24 -> 0 | N24: =E24*$E$20 -> 0 | O24: =+F24 -> 2200 | P24: =N24*O24 -> 0
A25: MAT | C25: Rodillo | D25: U | E25: =0/E20 -> 0 | F25: 6600 | G25: =+E25*F25 -> 0 | N25: =E25*$E$20 -> 0 | O25: =+F25 -> 6600 | P25: =N25*O25 -> 0
A26: MAT | C26: Primer pu 1000 | D26: lts | E26: 0 | F26: =12.57*1400 -> 17598 | G26: =+E26*F26 -> 0 | N26: =E26*$E$20 -> 0 | O26: =+F26 -> 17598 | P26: =N26*O26 -> 0
A27: MAT | C27: Poliurea en caliente | D27: kg | E27: 0 | F27: =13*1400 -> 18200 | G27: =+E27*F27 -> 0 | N27: =E27*$E$20 -> 0 | O27: =+F27 -> 18200 | P27: =N27*O27 -> 0
A28: MAT | C28: ARENA | D28: M3 | E28: =0/E20 -> 0 | F28: 20000 | G28: =+E28*F28 -> 0 | N28: =E28*$E$20 -> 0 | O28: =+F28 -> 20000 | P28: =N28*O28 -> 0
H30: =SUM(H11:H29) -> 7475211.8 | P30: =SUM(P11:P29) -> 7475211.8

Sheet Cascada
A4: CLIENTE:
A5: OBRA:
A6: FECHA:
A7: CONTACTO:
A8: ANÁLISIS DE PRECIOS
A10: RUBRO | B10: ITEM | C10: DENOMINACION | D10: UNIDAD | E10: CANTIDAD | F10: PRECIO UNIT SIN IVA | G10: PRECIO PARCIAL SIN IVA
A11: 1 | C11: COSTO - COSTO | G11: =SUM(G12:G14) -> 7475211.8
A12: 1 | B12: 1 | C12: MATERIALES | D12: GL | E12: 1 | F12: =SUMIF('Análisis de precios'!$A$9:$A$29,"MAT",'Análisis de precios'!$P$9:$P$29) -> 7241737.6 | G12: =+E12*F12 -> 7241737.6
A13: 1 | B13: 2 | C13: MANO DE OBRA | D13: GL | E13: 1 | F13: =SUMIF('Análisis de precios'!$A$9:$A$29,"MO",'Análisis de precios'!$P$9:$P$29) -> 233474.24 | G13: =+E13*F13 -> 233474.24
A14: 1 | B14: 3 | C14: EQUIPOS | D14: GL | E14: 1 | F14: =SUMIF('Análisis de precios'!$A$9:$A$10,"EQUIPOS",'Análisis de precios'!$P$9:$P$10) -> 0 | G14: =+E14*F14 -> 0
A16: 2 | C16: GASTOS GENERALES DIRECTOS | G16: =SUM(G17:G60) -> 444417.38 | H16: =G16/G11 -> 0.059452145
C17: Sueldos / Honorarios de Dirección de Obra | D17: Mes | E17: =2/25 -> 0.08 | F17: 1350000 | G17: =E17*F17 -> 108000
C18: Viáticos de Dirección de Obra | D18: Dia | E18: 0 | F18: 50000 | G18: =E18*F18 -> 0
C19: Alojamiento para Dirección de Obra | D19: Dia | E19: 0 | F19: 120000 | G19: =E19*F19 -> 0
C20: Combustible para movilidad de Dirección de Obra | D20: Km | E20: 0 | F20: 38000 | G20: =E20*F20 -> 0
C21: Mantenimiento vehicular de Dirección de Obra | D21: Km | E21: 2 | F21: 38000 | G21: =E21*F21 -> 76000
C22: Pasajes para Dirección de Obra | D22: U | E22: 1 | F22: 0 | G22: =E22*F22 -> 0
C23: Gastos varios de movilidad -Estacionamiento, peajes, etc- | D23: GL | E23: 0 | F23: 3000 | G23: =E23*F23 -> 0
C24: Librería | D24: GL | E24: 0 | F24: 0 | G24: =E24*F24 -> 0
C25: Seguros para Dirección de Obra | D25: Mes | E25: =5/25 -> 0.2 | F25: 15000 | G25: =E25*F25 -> 3000
C26: Indumentaria y EPP para Dirección de Obra | D26: JUEGO | E26: =5/25 -> 0.2 | F26: 220000 | G26: =E26*F26 -> 44000
G27: =E27*F27 -> 0
C28: Viáticos del personal operativo | D28: DIA | E28: 0 | F28: 0 | G28: =E28*F28 -> 0
C29: Alojamiento para personal operativo | D29: DIA | E29: 0 | F29: 0 | G29: =E29*F29 -> 0
C30: Combustible para movilidad de personal operativo | D30: KM | E30: 0 | F30: 0 | G30: =E30*F30 -> 0
C31: Mantenimiento vehicular para personal operativo | D31: KM | E31: 0 | F31: 0 | G31: =E31*F31 -> 0
C32: Pasajes para personal operativo | D32: U | E32: 0 | F32: 0 | G32: =E32*F32 -> 0
C33: Gastos varios de movilidad -Estacionamiento, peajes, etc- | D33: GL | E33: 0 | F33: 0 | G33: =E33*F33 -> 0
C34: Seguros para el personal operativo | D34: MES | E34: =3*5/25 -> 0.6 | F34: 15000 | G34: =E34*F34 -> 9000
C35: Indumentaria y EPP para el personal operativo | D35: JUEGO | E35: =3*5/25 -> 0.6 | F35: 220000 | G35: =E35*F35 -> 132000
G36: =E36*F36 -> 0
C37: Programa de Higiene y Seguridad | D37: GL | E37: 0 | F37: 0 | G37: =E37*F37 -> 0
C38: Sueldos / Honorarios de Resposable de Higiene y Seguridad | D38: GL | E38: 0 | F38: 0 | G38: =E38*F38 -> 0
C39: Elementos de señalización | D39: GL | E39: 0 | F39: 0 | G39: =E39*F39 -> 0
G40: =E40*F40 -> 0
C41: Fletes de materiales | D41: KM | E41: 0 | F41: 950 | G41: =E41*F41 -> 0
C42: Viáticos de chóferes | D42: DIA | E42: 0 | F42: 15000 | G42: =E42*F42 -> 0
C43: Alojamiento de chóferes | D43: DIA | E43: 0 | F43: 100000 | G43: =E43*F43 -> 0
C44: Combustible para movilidad de personal operativo | D44: DIA | E44: 0 | F44: =9*1100/100 -> 99 | G44: =E44*F44 -> 0
C45: Mantenimiento vehicular para personal de compras | D45: KM | E45: 0 | F45: =9*1100/100 -> 99 | G45: =E45*F45 -> 0
C46: Pasajes para personal de compras | D46: GL | E46: 0 | F46: 0 | G46: =E46*F46 -> 0
C47: Gastos varios de movilidad -Estacionamiento, peajes, etc- | D47: GL | E47: 0 | F47: 0 | G47: =E47*F47 -> 0
C48: Impuesto al cheque | D48: GL | E48: 0.01 | F48: =G12 -> 7241737.6 | G48: =E48*F48 -> 72417.376
G49: =E49*F49 -> 0
C50: Sueldo / Honorarios de Pañolero | D50: MES | E50: 0 | F50: 0 | G50: =E50*F50 -> 0
C51: Viáticos de Pañolero | D51: DIA | E51: 0 | F51: 0 | G51: =E51*F51 -> 0
C52: Alojamiento para Pañolero | D52: DIA | E52: 0 | F52: 0 | G52: =E52*F52 -> 0
C53: Gastos de movilidad de Pañolero | D53: DIA | E53: 0 | F53: 0 | G53: =E53*F53 -> 0
G54: =E54*F54 -> 0
C55: Sellados | D55: GL | E55: 0 | F55: 0 | G55: =E55*F55 -> 0
C56: Garantías para la Oferta | D56: GL | E56: 0 | F56: 0 | G56: =E56*F56 -> 0
C57: Garantías para la Ejecución | D57: GL | E57: 0 | F57: 0 | G57: =E57*F57 -> 0
C58: Fondo de Reparo | D58: GL | E58: 0 | F58: 0 | G58: =E58*F58 -> 0
A59: 2 | B59: 1 | C59: Impresiones y Librería para presentación de ofertas | D59: GL | E59: 0 | F59: 0 | G59: =E59*F59 -> 0
C60: Representacion Tecnica | D60: GL | E60: 0 | F60: 0 | G60: =E60*F60 -> 0
A62: 3 | C62: COSTO | G62: =+G11+G16 -> 7919629.2
A64: 4 | C64: GASTOS GENERALES INDIRECTOS | G64: =+G65 -> 1425533.3
A65: 4 | B65: 1 | C65: GASTOS GENERALES INDIRECTOS | D65: % | E65: 18 | G65: =+(G62*E65/100) -> 1425533.3
A67: 5 | C67: SUB TOTAL 1 | G67: =+G64+G62 -> 9345162.5
A69: 6 | C69: BENEFICIOS | G69: =+G70+G71 -> 3249979.2
A70: 6 | B70: 1 | C70: BENEFICIOS | D70: % | E70: 34.777129 | G70: =+G67*E70/100 -> 3249979.2
A71: 6 | B71: 2 | C71: COSTO FINANCIERO | D71: % | E71: 0 | G71: =+G67*E71/100 -> 0
A73: 7 | C73: SUB TOTAL 2 | G73: =+G67+G69 -> 12595142
J74: x M2 | K74: =G73/'Análisis de precios'!E11 -> 74089.069
A75: 8 | C75: IMPUESTOS | G75: =+G76+G77 -> 314878.54
C76: INGRESOS BRUTOS | D76: % | E76: 2.5 | G76: =+G73*E76/100 -> 314878.54
A78: 8 | C78: SUB TOTAL 3 | G78: =+G73+G75 -> 12910020
A80: 8 | C80: IMPUESTOS | G80: =+G81 -> 2644979.8 | J80: x M2 con iva | K80: =G83/'Análisis de precios'!E11 -> 91500
C81: IVA | D81: % | E81: 21 | G81: =+G73*E81/100 -> 2644979.8
A83: 9 | C83: PRECIO | G83: =+G78+G80+0.01 -> 15555000 | H83: =G83/G11 -> 2.0808775
G85: 13640520

Sheet Precio
A4: CLIENTE:
A5: OBRA:
A6: FECHA:
A7: CONTACTO:
A9: RUBRO | B9: ÍTEM | C9: DENOMINACIÓN | D9: UNIDAD | E9: CANTIDAD | F9: PRECIO UNITARIO | G9: PRECIO PARCIAL
B10: =+'Análisis de precios'!B11 -> 1 | C10: =+'Análisis de precios'!C11 -> APLICACIÓN DE DESMOPOL + SELLADO | D10: =+'Análisis de precios'!D11 -> M2 | E10: =+'Análisis de precios'!E11 -> 170 | F10: =+'Análisis de precios'!G11*Cascada!H83 -> 91500 | G10: =+E10*F10 -> 15555000
B11: =+'Análisis de precios'!B20 -> 2 | C11: =+'Análisis de precios'!C20 -> APLICACIÓN DE DESMOPOL + ARENA | D11: =+'Análisis de precios'!D11 -> M2 | E11: =+'Análisis de precios'!E20 -> 150 | F11: =+'Análisis de precios'!G20*Cascada!H83 -> 0 | G11: =+E11*F11 -> 0 | I11: =+E10+E11 -> 320 | J11: =+I11*60 -> 19200
F12: TOTAL | G12: =SUM(G10:G11) -> 15555000 | J12: =+J11*1420 -> 27264000
C14: DETALLE TÉCNICO DE LOS TRABAJOS A REALIZAR
C15: Provisión de materiales, equipos y mano de obra especializada
C17: Objeto de la obra:
C18: Impermeabilización sobre superficie de losa.
C20: Descripción de los trabajos:
C22: 1. Preparación de la superficie:
C23: Se realizará una limpieza manual exhaustiva de toda la superficie a intervenir, eliminando polvo, suciedad, restos de materiales y cualquier tipo de contaminante que pueda afectar la adherencia.
C24: Posteriormente, se procederá al sellado de grietas y fisuras mediante la aplicación de sellador elastomérico de alta resistencia.
C25: La superficie deberá quedar seca, firme, cohesionada y libre de partículas sueltas o humedad residual, condiciones indispensables para garantizar la correcta adherencia del sistema impermeabilizante.
C27: 2. Imprimación:
C28: Se aplicará una capa uniforme de imprimante promotor de adherencia, compatible con sistemas de base poliuretánica, asegurando la consolidación del sustrato y su correcta penetración en porosidades.
C30: 3. Impermeabilización:
... C42: Saldo restante a abonar dentro de los 30 días posteriores a la finalización de los trabajos.

Sheet Programa de trabajo
A4: CLIENTE:
A5: OBRA:
A6: FECHA:
A7: CONTACTO:
A8: ANÁLISIS DE PRECIOS
A10: RUBRO | B10: ÍTEM | C10: DENOMINACIÓN | D10: UNIDAD | E10: CANTIDAD | F10: DIA 1 | G10: DIA 2 | H10: DIA 3
B11: 1 | C11: APLICACIÓN DE DESMOPOL + SELLADO | D11: M2 | E11: 124.5
B12: 2 | C12: APLICACIÓN DE DESMOPOL + ARENA | D12: M2 | E12: 62.5

Sheet Insumos
A4: CLIENTE:
A5: OBRA:
A6: FECHA:
A7: CONTACTO:
A8: ANÁLISIS DE PRECIOS
A10: RUBRO | B10: ÍTEM | C10: DENOMINACIÓN | D10: UNIDAD | E10: CANTIDAD | G10: PRECIO UNITARIO
A11: MO | C11: Oficial | D11: hs | E11: =SUMIF('Análisis de precios'!C10:P29,C11,'Análisis de precios'!N10:$N$29) -> 16 | F11: 8036.37 | G11: =+E11*F11 -> 128581.92
A12: MO | C12: Ayudante | D12: hs | E12: =SUMIF('Análisis de precios'!C11:P30,C12,'Análisis de precios'!N11:$N$29) -> 16 | F12: =+(5619.37+4134.07)/2 -> 4876.72 | G12: =+E12*F12 -> 78027.52
A13: MAT | C13: bersell | D13: kg | E13: =SUMIF('Análisis de precios'!C12:P31,C13,'Análisis de precios'!N12:$N$29) -> 20 | F13: 9500 | G13: =+E13*F13 -> 190000
A14: MAT | C14: Pincel | D14: U | E14: =SUMIF('Análisis de precios'!C13:P32,C14,'Análisis de precios'!N13:$N$29) -> 3 | F14: 2100 | G14: =+E14*F14 -> 6300
A15: MAT | C15: Rodillo | D15: U | E15: =SUMIF('Análisis de precios'!C14:P33,C15,'Análisis de precios'!N14:$N$29) -> 3 | F15: 6600 | G15: =+E15*F15 -> 19800
A16: MAT | C16: Primer pu 1000 | D16: lts | E16: =SUMIF('Análisis de precios'!C15:P34,C16,'Análisis de precios'!N15:$N$29) -> 51 | F16: =12.57*1400 -> 17598 | G16: =+E16*F16 -> 897498
A17: MAT | C17: Poliurea en caliente | D17: kg | E17: =SUMIF('Análisis de precios'!C16:P35,C17,'Análisis de precios'!N16:$N$29) -> 255 | F17: =13*1400 -> 18200 | G17: =+E17*F17 -> 4641000
A18: MAT | C18: Alifatico | D18: lts | E18: =SUMIF('Análisis de precios'!C17:P36,C18,'Análisis de precios'!N17:$N$29) -> 51 | F18: =13.06*1400 -> 18284 | G18: =+E18*F18 -> 932484
A19: MAT | C19: ARENA | D19: M3 | E19: =SUMIF('Análisis de precios'!C18:P37,C19,'Análisis de precios'!N18:$N$29) -> 0 | F19: 20000 | G19: =+E19*F19 -> 0
E20: TOTAL | G20: =SUM(G11:G19) -> 6893691.4
